LynqX/__init__.py
LynqX/__main__.py
LynqX/app.py
lynqx-1.0.6.dist-info/licenses/LICENSE
lynqx-1.0.6.dist-info/METADATA
lynqx-1.0.6.dist-info/WHEEL
lynqx-1.0.6.dist-info/entry_points.txt
lynqx-1.0.6.dist-info/top_level.txt
lynqx-1.0.6.dist-info/RECORD
