Metadata-Version: 2.4
Name: LynqX
Version: 1.0.6
Summary: A Textual-based terminal chat client offering real-time messaging, file sharing, typing indicators, and emoji support.
Author: MD. Shahariar Ahmmed Shovon
Author-email: shovonali885@gmail.com
License: MIT
Project-URL: Homepage, https://github.com/SwagCoder18/LynqX
Requires-Python: >=3.12
License-File: LICENSE
Requires-Dist: textual
Requires-Dist: httpx
Requires-Dist: requests
Requires-Dist: sseclient
Requires-Dist: emoji
Requires-Dist: websockets
Dynamic: license-file
